{"updatedAt":"2026-06-23T21:45:40.905Z","market":{"score":-3,"direction":"bear","btc":{"align":"역배열","rsi":40.98549297822106},"breadth":{"long":9,"short":54,"total":227,"score":-1}},"symbols":[{"symbol":"BTCUSDT","price":62624.01,"change24h":-2.43,"rsi":41,"ema7":62482.625687,"ema24":62918.754025,"ema60":63458.211867,"align":"역배열","vsEma24":-0.47,"isStock":false},{"symbol":"ETHUSDT","price":1667.06,"change24h":-3.6,"rsi":38.3,"ema7":1662.826083,"ema24":1680.359982,"ema60":1703.580231,"align":"역배열","vsEma24":-0.79,"isStock":false},{"symbol":"TAOUSDT","price":220.2,"change24h":-4.39,"rsi":45.2,"ema7":218.318577,"ema24":221.191842,"ema60":226.023581,"align":"역배열","vsEma24":-0.45,"isStock":false},{"symbol":"SOLUSDT","price":69.25,"change24h":-4.39,"rsi":36.8,"ema7":69.053437,"ema24":69.991592,"ema60":71.214826,"align":"역배열","vsEma24":-1.06,"isStock":false},{"symbol":"XRPUSDT","price":1.1049,"change24h":-2.06,"rsi":41,"ema7":1.102764,"ema24":1.110628,"ema60":1.123926,"align":"역배열","vsEma24":-0.52,"isStock":false},{"symbol":"ZECUSDT","price":417.1,"change24h":-6.28,"rsi":33.2,"ema7":417.259719,"ema24":426.400312,"ema60":438.947181,"align":"역배열","vsEma24":-2.18,"isStock":false},{"symbol":"WLDUSDT","price":0.5435,"change24h":-13.66,"rsi":29.1,"ema7":0.547082,"ema24":0.572232,"ema60":0.595528,"align":"역배열","vsEma24":-5.02,"isStock":false},{"symbol":"BNBUSDT","price":577.2,"change24h":-2.14,"rsi":41.8,"ema7":575.786888,"ema24":579.491532,"ema60":584.26824,"align":"역배열","vsEma24":-0.4,"isStock":false},{"symbol":"DOGEUSDT","price":0.07871,"change24h":-4.65,"rsi":29.4,"ema7":0.078747,"ema24":0.079957,"ema60":0.081469,"align":"역배열","vsEma24":-1.56,"isStock":false},{"symbol":"NEARUSDT","price":1.996,"change24h":-5.53,"rsi":39.9,"ema7":1.98898,"ema24":2.018172,"ema60":2.075368,"align":"역배열","vsEma24":-1.1,"isStock":false},{"symbol":"TRXUSDT","price":0.3292,"change24h":-1.29,"rsi":40.3,"ema7":0.329433,"ema24":0.330322,"ema60":0.329625,"align":"혼조","vsEma24":-0.34,"isStock":false},{"symbol":"SUIUSDT","price":0.7007,"change24h":-2.54,"rsi":46.3,"ema7":0.699959,"ema24":0.70448,"ema60":0.709669,"align":"역배열","vsEma24":-0.54,"isStock":false},{"symbol":"TONUSDT","price":1.563,"change24h":-7.68,"rsi":40.8,"ema7":1.56702,"ema24":1.602073,"ema60":1.629172,"align":"역배열","vsEma24":-2.44,"isStock":false},{"symbol":"ADAUSDT","price":0.1509,"change24h":-4.79,"rsi":34.8,"ema7":0.150699,"ema24":0.153405,"ema60":0.156797,"align":"역배열","vsEma24":-1.63,"isStock":false},{"symbol":"AVAXUSDT","price":6.43,"change24h":3.26,"rsi":64,"ema7":6.358183,"ema24":6.299638,"ema60":6.274657,"align":"정배열","vsEma24":2.07,"isStock":false},{"symbol":"RESOLVUSDT","price":0.024,"change24h":10.09,"rsi":51.5,"ema7":0.024141,"ema24":0.023843,"ema60":0.022269,"align":"정배열","vsEma24":0.66,"isStock":false},{"symbol":"DEXEUSDT","price":23.075,"change24h":28.59,"rsi":63.9,"ema7":23.058972,"ema24":21.931418,"ema60":19.539293,"align":"정배열","vsEma24":5.21,"isStock":false},{"symbol":"BCHUSDT","price":194,"change24h":-1.97,"rsi":53.1,"ema7":192.071249,"ema24":192.994163,"ema60":195.542488,"align":"역배열","vsEma24":0.52,"isStock":false},{"symbol":"ENAUSDT","price":0.0871,"change24h":-5.43,"rsi":45.6,"ema7":0.086364,"ema24":0.087672,"ema60":0.089354,"align":"역배열","vsEma24":-0.65,"isStock":false},{"symbol":"LINKUSDT","price":7.608,"change24h":-3.5,"rsi":38.7,"ema7":7.594798,"ema24":7.679176,"ema60":7.795015,"align":"역배열","vsEma24":-0.93,"isStock":false},{"symbol":"AAVEUSDT","price":72.48,"change24h":-3.22,"rsi":43.7,"ema7":72.232026,"ema24":73.017642,"ema60":73.920141,"align":"역배열","vsEma24":-0.74,"isStock":false},{"symbol":"XLMUSDT","price":0.1957,"change24h":-4.02,"rsi":43.9,"ema7":0.19449,"ema24":0.196737,"ema60":0.203108,"align":"역배열","vsEma24":-0.53,"isStock":false},{"symbol":"PEPEUSDT","price":0.000003,"change24h":-3.91,"rsi":36.2,"ema7":0.000003,"ema24":0.000003,"ema60":0.000003,"align":"역배열","vsEma24":-1.31,"isStock":false},{"symbol":"LTCUSDT","price":41.99,"change24h":-5.77,"rsi":22.3,"ema7":42.142594,"ema24":43.101392,"ema60":43.883942,"align":"역배열","vsEma24":-2.58,"isStock":false},{"symbol":"UNIUSDT","price":2.927,"change24h":-2.14,"rsi":49.7,"ema7":2.906526,"ema24":2.923311,"ema60":2.966631,"align":"역배열","vsEma24":0.13,"isStock":false},{"symbol":"LAYERUSDT","price":0.0717,"change24h":-4.14,"rsi":44.2,"ema7":0.071938,"ema24":0.074143,"ema60":0.073042,"align":"혼조","vsEma24":-3.29,"isStock":false},{"symbol":"ONDOUSDT","price":0.3155,"change24h":-4.25,"rsi":44.2,"ema7":0.312837,"ema24":0.317072,"ema60":0.326352,"align":"역배열","vsEma24":-0.5,"isStock":false},{"symbol":"FETUSDT","price":0.1747,"change24h":-2.89,"rsi":44.8,"ema7":0.173773,"ema24":0.175987,"ema60":0.180316,"align":"역배열","vsEma24":-0.73,"isStock":false},{"symbol":"HYPERUSDT","price":0.078,"change24h":-2.37,"rsi":46.3,"ema7":0.077935,"ema24":0.07868,"ema60":0.079421,"align":"역배열","vsEma24":-0.86,"isStock":false},{"symbol":"FILUSDT","price":0.79,"change24h":0.64,"rsi":55.4,"ema7":0.780872,"ema24":0.779142,"ema60":0.786308,"align":"혼조","vsEma24":1.39,"isStock":false},{"symbol":"IDUSDT","price":0.034,"change24h":-12.37,"rsi":43.2,"ema7":0.033866,"ema24":0.035073,"ema60":0.03453,"align":"혼조","vsEma24":-3.06,"isStock":false},{"symbol":"DASHUSDT","price":36.15,"change24h":4.75,"rsi":66.6,"ema7":35.668993,"ema24":35.22124,"ema60":35.357241,"align":"혼조","vsEma24":2.64,"isStock":false},{"symbol":"DYDXUSDT","price":0.14859,"change24h":13.91,"rsi":68.9,"ema7":0.142578,"ema24":0.1368,"ema60":0.131567,"align":"정배열","vsEma24":8.62,"isStock":false},{"symbol":"TIAUSDT","price":0.3829,"change24h":-1.34,"rsi":49.4,"ema7":0.382626,"ema24":0.383397,"ema60":0.383018,"align":"혼조","vsEma24":-0.13,"isStock":false},{"symbol":"EIGENUSDT","price":0.2507,"change24h":-13.49,"rsi":35.5,"ema7":0.251764,"ema24":0.261026,"ema60":0.268076,"align":"역배열","vsEma24":-3.96,"isStock":false},{"symbol":"INJUSDT","price":4.595,"change24h":-4.86,"rsi":41.9,"ema7":4.574361,"ema24":4.638469,"ema60":4.775693,"align":"역배열","vsEma24":-0.94,"isStock":false},{"symbol":"DOTUSDT","price":0.91,"change24h":-3.5,"rsi":44.5,"ema7":0.905024,"ema24":0.914157,"ema60":0.933388,"align":"역배열","vsEma24":-0.45,"isStock":false},{"symbol":"HBARUSDT","price":0.07772,"change24h":-1.67,"rsi":43.9,"ema7":0.077559,"ema24":0.077972,"ema60":0.07869,"align":"역배열","vsEma24":-0.32,"isStock":false},{"symbol":"JTOUSDT","price":0.6641,"change24h":-0.13,"rsi":57.3,"ema7":0.650915,"ema24":0.647928,"ema60":0.660351,"align":"혼조","vsEma24":2.5,"isStock":false},{"symbol":"ALGOUSDT","price":0.0952,"change24h":6.13,"rsi":65.1,"ema7":0.094149,"ema24":0.092636,"ema60":0.092147,"align":"정배열","vsEma24":2.77,"isStock":false},{"symbol":"LDOUSDT","price":0.2601,"change24h":-3.67,"rsi":46.4,"ema7":0.258109,"ema24":0.261069,"ema60":0.266976,"align":"역배열","vsEma24":-0.37,"isStock":false},{"symbol":"ICPUSDT","price":2.209,"change24h":-1.78,"rsi":54.4,"ema7":2.173978,"ema24":2.189323,"ema60":2.223094,"align":"역배열","vsEma24":0.9,"isStock":false},{"symbol":"AXSUSDT","price":1.019,"change24h":-3.32,"rsi":42.6,"ema7":1.020582,"ema24":1.03408,"ema60":1.050458,"align":"역배열","vsEma24":-1.46,"isStock":false},{"symbol":"CHZUSDT","price":0.01951,"change24h":-3.27,"rsi":49.5,"ema7":0.019281,"ema24":0.019469,"ema60":0.020143,"align":"역배열","vsEma24":0.21,"isStock":false},{"symbol":"ARBUSDT","price":0.0791,"change24h":-5.04,"rsi":41,"ema7":0.078816,"ema24":0.079998,"ema60":0.081736,"align":"역배열","vsEma24":-1.12,"isStock":false},{"symbol":"TSTUSDT","price":0.01119,"change24h":2.47,"rsi":48,"ema7":0.011343,"ema24":0.011283,"ema60":0.011242,"align":"정배열","vsEma24":-0.82,"isStock":false},{"symbol":"RENDERUSDT","price":1.579,"change24h":-4.07,"rsi":42.6,"ema7":1.571427,"ema24":1.59017,"ema60":1.630239,"align":"역배열","vsEma24":-0.7,"isStock":false},{"symbol":"ZROUSDT","price":0.933,"change24h":-3.91,"rsi":44.6,"ema7":0.935568,"ema24":0.945032,"ema60":0.944691,"align":"혼조","vsEma24":-1.27,"isStock":false},{"symbol":"APTUSDT","price":0.65,"change24h":-1.51,"rsi":56.2,"ema7":0.64062,"ema24":0.642808,"ema60":0.64871,"align":"역배열","vsEma24":1.12,"isStock":false},{"symbol":"POLUSDT","price":0.0776,"change24h":-2.56,"rsi":44.3,"ema7":0.077521,"ema24":0.078,"ema60":0.078764,"align":"역배열","vsEma24":-0.51,"isStock":false},{"symbol":"TNSRUSDT","price":0.0345,"change24h":-11.76,"rsi":32.9,"ema7":0.034683,"ema24":0.036242,"ema60":0.037675,"align":"역배열","vsEma24":-4.81,"isStock":false},{"symbol":"LUNCUSDT","price":0.000064,"change24h":-1.38,"rsi":48.2,"ema7":0.000064,"ema24":0.000064,"ema60":0.000066,"align":"역배열","vsEma24":-0.07,"isStock":false},{"symbol":"WUSDT","price":0.01037,"change24h":-12.86,"rsi":36.9,"ema7":0.010414,"ema24":0.01073,"ema60":0.010938,"align":"역배열","vsEma24":-3.36,"isStock":false},{"symbol":"LRCUSDT","price":0.01879,"change24h":-6.24,"rsi":34.9,"ema7":0.019606,"ema24":0.01994,"ema60":0.020647,"align":"역배열","vsEma24":-5.77,"isStock":false},{"symbol":"SHIBUSDT","price":0.000005,"change24h":-1.93,"rsi":47,"ema7":0.000005,"ema24":0.000005,"ema60":0.000005,"align":"역배열","vsEma24":-0.19,"isStock":false},{"symbol":"BIOUSDT","price":0.02994,"change24h":-0.73,"rsi":54.5,"ema7":0.02976,"ema24":0.029574,"ema60":0.030393,"align":"혼조","vsEma24":1.24,"isStock":false},{"symbol":"PENDLEUSDT","price":1.307,"change24h":-4.53,"rsi":37.8,"ema7":1.305671,"ema24":1.328752,"ema60":1.364884,"align":"역배열","vsEma24":-1.64,"isStock":false},{"symbol":"JSTUSDT","price":0.08307,"change24h":-0.59,"rsi":49.6,"ema7":0.083276,"ema24":0.083098,"ema60":0.083032,"align":"정배열","vsEma24":-0.03,"isStock":false},{"symbol":"SUSDT","price":0.02416,"change24h":-4.05,"rsi":40.5,"ema7":0.024052,"ema24":0.024696,"ema60":0.025958,"align":"역배열","vsEma24":-2.17,"isStock":false},{"symbol":"STGUSDT","price":0.1825,"change24h":-15.55,"rsi":36.7,"ema7":0.184236,"ema24":0.19143,"ema60":0.19953,"align":"역배열","vsEma24":-4.66,"isStock":false},{"symbol":"ARUSDT","price":2.02,"change24h":1.05,"rsi":57.6,"ema7":2.009063,"ema24":1.993211,"ema60":1.995732,"align":"혼조","vsEma24":1.34,"isStock":false},{"symbol":"SEIUSDT","price":0.05237,"change24h":-3.41,"rsi":38.8,"ema7":0.052284,"ema24":0.05301,"ema60":0.053819,"align":"역배열","vsEma24":-1.21,"isStock":false},{"symbol":"SAGAUSDT","price":0.01437,"change24h":-1.64,"rsi":40.7,"ema7":0.014485,"ema24":0.014723,"ema60":0.014776,"align":"역배열","vsEma24":-2.4,"isStock":false},{"symbol":"RUNEUSDT","price":0.42,"change24h":6.06,"rsi":53,"ema7":0.419347,"ema24":0.418383,"ema60":0.4153,"align":"정배열","vsEma24":0.39,"isStock":false},{"symbol":"ETCUSDT","price":7.03,"change24h":-2.22,"rsi":47.7,"ema7":6.977051,"ema24":7.035826,"ema60":7.16617,"align":"역배열","vsEma24":-0.08,"isStock":false},{"symbol":"ORDIUSDT","price":3.168,"change24h":-2.73,"rsi":49.4,"ema7":3.134423,"ema24":3.1643,"ema60":3.22293,"align":"역배열","vsEma24":0.12,"isStock":false},{"symbol":"GALAUSDT","price":0.00243,"change24h":-4.71,"rsi":35.4,"ema7":0.002432,"ema24":0.002474,"ema60":0.002536,"align":"역배열","vsEma24":-1.77,"isStock":false},{"symbol":"HMSTRUSDT","price":0.000166,"change24h":-3.94,"rsi":39.7,"ema7":0.000167,"ema24":0.000171,"ema60":0.000172,"align":"역배열","vsEma24":-3.05,"isStock":false},{"symbol":"ZENUSDT","price":4.392,"change24h":-2.44,"rsi":46.7,"ema7":4.358737,"ema24":4.401793,"ema60":4.479743,"align":"역배열","vsEma24":-0.22,"isStock":false},{"symbol":"EDUUSDT","price":0.0302,"change24h":4.86,"rsi":58.5,"ema7":0.030154,"ema24":0.029429,"ema60":0.029288,"align":"정배열","vsEma24":2.62,"isStock":false},{"symbol":"ETHFIUSDT","price":0.349,"change24h":0.87,"rsi":62.5,"ema7":0.342501,"ema24":0.339417,"ema60":0.341977,"align":"혼조","vsEma24":2.82,"isStock":false},{"symbol":"WIFUSDT","price":0.1581,"change24h":-3.54,"rsi":46.2,"ema7":0.15676,"ema24":0.158808,"ema60":0.161334,"align":"역배열","vsEma24":-0.45,"isStock":false},{"symbol":"FLOKIUSDT","price":0.000024,"change24h":-5.25,"rsi":34.9,"ema7":0.000024,"ema24":0.000024,"ema60":0.000025,"align":"역배열","vsEma24":-1.58,"isStock":false},{"symbol":"VIRTUALUSDT","price":0.5747,"change24h":-2.43,"rsi":48.7,"ema7":0.571344,"ema24":0.574572,"ema60":0.584958,"align":"역배열","vsEma24":0.02,"isStock":false},{"symbol":"IOUSDT","price":0.1836,"change24h":-4.57,"rsi":48.7,"ema7":0.181754,"ema24":0.183516,"ema60":0.187891,"align":"역배열","vsEma24":0.05,"isStock":false},{"symbol":"ATOMUSDT","price":1.731,"change24h":-3.78,"rsi":39.1,"ema7":1.730549,"ema24":1.753021,"ema60":1.774325,"align":"역배열","vsEma24":-1.26,"isStock":false},{"symbol":"PARTIUSDT","price":0.0545,"change24h":-8.4,"rsi":37.7,"ema7":0.055004,"ema24":0.057134,"ema60":0.057937,"align":"역배열","vsEma24":-4.61,"isStock":false},{"symbol":"OPUSDT","price":0.0993,"change24h":-1.49,"rsi":48.6,"ema7":0.098773,"ema24":0.09938,"ema60":0.100665,"align":"역배열","vsEma24":-0.08,"isStock":false},{"symbol":"BONKUSDT","price":0.000004,"change24h":-3.71,"rsi":44.2,"ema7":0.000004,"ema24":0.000004,"ema60":0.000005,"align":"역배열","vsEma24":-0.64,"isStock":false},{"symbol":"CRVUSDT","price":0.2043,"change24h":-2.53,"rsi":44.8,"ema7":0.204528,"ema24":0.205846,"ema60":0.208661,"align":"역배열","vsEma24":-0.75,"isStock":false},{"symbol":"SCRUSDT","price":0.0302,"change24h":0.37,"rsi":42.3,"ema7":0.03054,"ema24":0.031001,"ema60":0.031214,"align":"역배열","vsEma24":-2.58,"isStock":false},{"symbol":"PORTALUSDT","price":0.01473,"change24h":-5.21,"rsi":46.3,"ema7":0.01476,"ema24":0.014865,"ema60":0.015065,"align":"역배열","vsEma24":-0.91,"isStock":false},{"symbol":"BERAUSDT","price":0.219,"change24h":-3.95,"rsi":42.2,"ema7":0.217878,"ema24":0.221977,"ema60":0.226651,"align":"역배열","vsEma24":-1.34,"isStock":false},{"symbol":"NEIROUSDT","price":0.000064,"change24h":-3.98,"rsi":40.8,"ema7":0.000064,"ema24":0.000065,"ema60":0.000066,"align":"역배열","vsEma24":-0.89,"isStock":false},{"symbol":"PHBUSDT","price":0.015,"change24h":-70,"rsi":16.5,"ema7":0.027377,"ema24":0.037789,"ema60":0.046892,"align":"역배열","vsEma24":-60.31,"isStock":false},{"symbol":"APEUSDT","price":0.1321,"change24h":-4.76,"rsi":37,"ema7":0.132621,"ema24":0.134815,"ema60":0.136244,"align":"역배열","vsEma24":-2.01,"isStock":false},{"symbol":"QNTUSDT","price":70.43,"change24h":0.83,"rsi":52.9,"ema7":70.392199,"ema24":70.037643,"ema60":70.195651,"align":"혼조","vsEma24":0.56,"isStock":false},{"symbol":"MEMEUSDT","price":0.000546,"change24h":1.68,"rsi":63.2,"ema7":0.000535,"ema24":0.000531,"ema60":0.000538,"align":"혼조","vsEma24":2.81,"isStock":false},{"symbol":"BANANAS31USDT","price":0.008768,"change24h":-9.21,"rsi":35.1,"ema7":0.008841,"ema24":0.009137,"ema60":0.009378,"align":"역배열","vsEma24":-4.04,"isStock":false},{"symbol":"NMRUSDT","price":9.07,"change24h":-0.33,"rsi":46.1,"ema7":9.171045,"ema24":9.144908,"ema60":9.079083,"align":"정배열","vsEma24":-0.82,"isStock":false},{"symbol":"STRKUSDT","price":0.0322,"change24h":-3.59,"rsi":40.3,"ema7":0.032084,"ema24":0.032539,"ema60":0.033253,"align":"역배열","vsEma24":-1.04,"isStock":false},{"symbol":"HIGHUSDT","price":0.034,"change24h":-22.73,"rsi":27.7,"ema7":0.035628,"ema24":0.039441,"ema60":0.042351,"align":"역배열","vsEma24":-13.79,"isStock":false},{"symbol":"SANDUSDT","price":0.05274,"change24h":-4.53,"rsi":39.5,"ema7":0.05257,"ema24":0.053276,"ema60":0.054487,"align":"역배열","vsEma24":-1.01,"isStock":false},{"symbol":"PYTHUSDT","price":0.0354,"change24h":-3.28,"rsi":45.2,"ema7":0.03532,"ema24":0.035644,"ema60":0.036139,"align":"역배열","vsEma24":-0.68,"isStock":false},{"symbol":"BABYUSDT","price":0.01336,"change24h":-2.2,"rsi":48.6,"ema7":0.013265,"ema24":0.013372,"ema60":0.013693,"align":"역배열","vsEma24":-0.09,"isStock":false},{"symbol":"WALUSDT","price":0.0348,"change24h":-4.66,"rsi":46.8,"ema7":0.034613,"ema24":0.034994,"ema60":0.035242,"align":"역배열","vsEma24":-0.55,"isStock":false},{"symbol":"OMNIUSDT","price":3.88,"change24h":-6.51,"rsi":47.4,"ema7":3.943381,"ema24":3.928351,"ema60":3.869352,"align":"정배열","vsEma24":-1.23,"isStock":false},{"symbol":"RDNTUSDT","price":0.00328,"change24h":-19.41,"rsi":21.8,"ema7":0.00352,"ema24":0.003798,"ema60":0.004025,"align":"역배열","vsEma24":-13.64,"isStock":false},{"symbol":"PIXELUSDT","price":0.00513,"change24h":-5.35,"rsi":37.8,"ema7":0.005133,"ema24":0.005204,"ema60":0.005302,"align":"역배열","vsEma24":-1.43,"isStock":false},{"symbol":"ARKMUSDT","price":0.121,"change24h":-5.84,"rsi":35.6,"ema7":0.121388,"ema24":0.12318,"ema60":0.126593,"align":"역배열","vsEma24":-1.77,"isStock":false},{"symbol":"ATAUSDT","price":0.0012,"change24h":-53.85,"rsi":28.1,"ema7":0.001467,"ema24":0.001928,"ema60":0.00248,"align":"역배열","vsEma24":-37.76,"isStock":false},{"symbol":"ZKUSDT","price":0.01096,"change24h":-4.86,"rsi":37.2,"ema7":0.010935,"ema24":0.011127,"ema60":0.011384,"align":"역배열","vsEma24":-1.5,"isStock":false},{"symbol":"RAREUSDT","price":0.0122,"change24h":-4.69,"rsi":35.4,"ema7":0.012277,"ema24":0.012503,"ema60":0.012854,"align":"역배열","vsEma24":-2.42,"isStock":false},{"symbol":"DYMUSDT","price":0.0177,"change24h":-1.67,"rsi":42.3,"ema7":0.017865,"ema24":0.018083,"ema60":0.018227,"align":"역배열","vsEma24":-2.12,"isStock":false},{"symbol":"ZILUSDT","price":0.00305,"change24h":-1.61,"rsi":48,"ema7":0.003035,"ema24":0.003052,"ema60":0.003089,"align":"역배열","vsEma24":-0.07,"isStock":false},{"symbol":"EOSUSDT","price":0.7799,"change24h":-0.66,"rsi":69.6,"ema7":0.76448,"ema24":0.748277,"ema60":0.745071,"align":"정배열","vsEma24":4.23,"isStock":false},{"symbol":"STORJUSDT","price":0.073,"change24h":-2.54,"rsi":39.8,"ema7":0.072979,"ema24":0.074186,"ema60":0.075517,"align":"역배열","vsEma24":-1.6,"isStock":false},{"symbol":"OGNUSDT","price":0.01625,"change24h":-0.67,"rsi":54.6,"ema7":0.015998,"ema24":0.016092,"ema60":0.016407,"align":"역배열","vsEma24":0.98,"isStock":false},{"symbol":"LOKAUSDT","price":0.1237,"change24h":3.86,"rsi":64.9,"ema7":0.119778,"ema24":0.116911,"ema60":0.115949,"align":"정배열","vsEma24":5.81,"isStock":false},{"symbol":"REDUSDT","price":0.1009,"change24h":-7.52,"rsi":34.6,"ema7":0.101096,"ema24":0.103602,"ema60":0.105795,"align":"역배열","vsEma24":-2.61,"isStock":false},{"symbol":"IOTAUSDT","price":0.0418,"change24h":-4.57,"rsi":41.3,"ema7":0.041684,"ema24":0.042203,"ema60":0.043291,"align":"역배열","vsEma24":-0.96,"isStock":false},{"symbol":"SXPUSDT","price":0.0022,"change24h":-45,"rsi":23.7,"ema7":0.002584,"ema24":0.003327,"ema60":0.004144,"align":"역배열","vsEma24":-33.87,"isStock":false},{"symbol":"CYBERUSDT","price":0.351,"change24h":-4.1,"rsi":40.9,"ema7":0.350193,"ema24":0.355935,"ema60":0.361271,"align":"역배열","vsEma24":-1.39,"isStock":false},{"symbol":"FORMUSDT","price":0.2338,"change24h":-3.94,"rsi":43.5,"ema7":0.232021,"ema24":0.23554,"ema60":0.239571,"align":"역배열","vsEma24":-0.74,"isStock":false},{"symbol":"JASMYUSDT","price":0.00467,"change24h":1.08,"rsi":62,"ema7":0.004577,"ema24":0.004567,"ema60":0.004615,"align":"혼조","vsEma24":2.25,"isStock":false},{"symbol":"BNXUSDT","price":1.7819,"change24h":2.81,"rsi":54.3,"ema7":1.833459,"ema24":1.711944,"ema60":1.50865,"align":"정배열","vsEma24":4.09,"isStock":false},{"symbol":"ENJUSDT","price":0.03112,"change24h":-6.57,"rsi":35.9,"ema7":0.031128,"ema24":0.031701,"ema60":0.032726,"align":"역배열","vsEma24":-1.83,"isStock":false},{"symbol":"XAIUSDT","price":0.00754,"change24h":-4.56,"rsi":35.4,"ema7":0.007564,"ema24":0.007711,"ema60":0.007902,"align":"역배열","vsEma24":-2.22,"isStock":false},{"symbol":"KAVAUSDT","price":0.04745,"change24h":0.13,"rsi":50.1,"ema7":0.047496,"ema24":0.047436,"ema60":0.047518,"align":"혼조","vsEma24":0.03,"isStock":false},{"symbol":"SNXUSDT","price":0.229,"change24h":-6.53,"rsi":38.5,"ema7":0.229341,"ema24":0.234164,"ema60":0.238295,"align":"역배열","vsEma24":-2.21,"isStock":false},{"symbol":"VETUSDT","price":0.004692,"change24h":-4.22,"rsi":41.7,"ema7":0.004676,"ema24":0.00474,"ema60":0.004819,"align":"역배열","vsEma24":-1,"isStock":false},{"symbol":"ACEUSDT","price":0.0763,"change24h":-3.54,"rsi":41.7,"ema7":0.076063,"ema24":0.077412,"ema60":0.079826,"align":"역배열","vsEma24":-1.44,"isStock":false},{"symbol":"DOGSUSDT","price":0.000041,"change24h":-2.4,"rsi":48.2,"ema7":0.00004,"ema24":0.000041,"ema60":0.000041,"align":"역배열","vsEma24":-0.23,"isStock":false},{"symbol":"PNUTUSDT","price":0.0437,"change24h":-2.02,"rsi":49.9,"ema7":0.043412,"ema24":0.043634,"ema60":0.044158,"align":"역배열","vsEma24":0.15,"isStock":false},{"symbol":"EPICUSDT","price":0.458,"change24h":2.92,"rsi":61.2,"ema7":0.45458,"ema24":0.449184,"ema60":0.451582,"align":"혼조","vsEma24":1.96,"isStock":false},{"symbol":"ACHUSDT","price":0.00485,"change24h":-2.81,"rsi":49,"ema7":0.004807,"ema24":0.004845,"ema60":0.004954,"align":"역배열","vsEma24":0.1,"isStock":false},{"symbol":"ROSEUSDT","price":0.00642,"change24h":-2.28,"rsi":48.8,"ema7":0.006387,"ema24":0.00642,"ema60":0.006517,"align":"역배열","vsEma24":-0.01,"isStock":false},{"symbol":"BOMEUSDT","price":0.000419,"change24h":-3.9,"rsi":44.4,"ema7":0.000416,"ema24":0.000421,"ema60":0.000431,"align":"역배열","vsEma24":-0.56,"isStock":false},{"symbol":"SUPERUSDT","price":0.0899,"change24h":-3.64,"rsi":37.9,"ema7":0.089927,"ema24":0.09091,"ema60":0.093063,"align":"역배열","vsEma24":-1.11,"isStock":false},{"symbol":"RSRUSDT","price":0.001251,"change24h":-1.96,"rsi":45,"ema7":0.001247,"ema24":0.001257,"ema60":0.001277,"align":"역배열","vsEma24":-0.51,"isStock":false},{"symbol":"ALTUSDT","price":0.00605,"change24h":-3.51,"rsi":39.8,"ema7":0.006039,"ema24":0.006112,"ema60":0.006264,"align":"역배열","vsEma24":-1.01,"isStock":false},{"symbol":"FUNUSDT","price":0.000342,"change24h":-24.34,"rsi":31.1,"ema7":0.000352,"ema24":0.000386,"ema60":0.000421,"align":"역배열","vsEma24":-11.49,"isStock":false},{"symbol":"NFPUSDT","price":0.0073,"change24h":-1.48,"rsi":48.2,"ema7":0.00733,"ema24":0.007321,"ema60":0.007427,"align":"혼조","vsEma24":-0.29,"isStock":false},{"symbol":"NILUSDT","price":0.03728,"change24h":-3.49,"rsi":43.8,"ema7":0.037126,"ema24":0.037599,"ema60":0.038482,"align":"역배열","vsEma24":-0.85,"isStock":false},{"symbol":"KAITOUSDT","price":0.4443,"change24h":-4.47,"rsi":37.7,"ema7":0.443904,"ema24":0.450128,"ema60":0.460374,"align":"역배열","vsEma24":-1.29,"isStock":false},{"symbol":"OMUSDT","price":0.0669,"change24h":-5.11,"rsi":39.3,"ema7":0.068905,"ema24":0.069292,"ema60":0.06829,"align":"혼조","vsEma24":-3.45,"isStock":false},{"symbol":"AIXBTUSDT","price":0.02193,"change24h":-2.23,"rsi":47.3,"ema7":0.021816,"ema24":0.021979,"ema60":0.022394,"align":"역배열","vsEma24":-0.22,"isStock":false},{"symbol":"MANAUSDT","price":0.0716,"change24h":-1.24,"rsi":49.3,"ema7":0.071148,"ema24":0.071562,"ema60":0.072365,"align":"역배열","vsEma24":0.05,"isStock":false},{"symbol":"GRTUSDT","price":0.01907,"change24h":-2.15,"rsi":47,"ema7":0.018964,"ema24":0.019115,"ema60":0.019375,"align":"역배열","vsEma24":-0.23,"isStock":false},{"symbol":"IMXUSDT","price":0.1387,"change24h":0.65,"rsi":58,"ema7":0.137298,"ema24":0.136632,"ema60":0.138285,"align":"혼조","vsEma24":1.51,"isStock":false},{"symbol":"BSWUSDT","price":0.0112,"change24h":-8.94,"rsi":12.9,"ema7":0.012753,"ema24":0.014653,"ema60":0.016493,"align":"역배열","vsEma24":-23.57,"isStock":false},{"symbol":"KERNELUSDT","price":0.0429,"change24h":-5.3,"rsi":43.7,"ema7":0.042572,"ema24":0.043254,"ema60":0.045251,"align":"역배열","vsEma24":-0.82,"isStock":false},{"symbol":"GMTUSDT","price":0.00795,"change24h":-2.93,"rsi":44.7,"ema7":0.007916,"ema24":0.007986,"ema60":0.008115,"align":"역배열","vsEma24":-0.45,"isStock":false},{"symbol":"ACTUSDT","price":0.0083,"change24h":-1.77,"rsi":47.3,"ema7":0.008292,"ema24":0.008328,"ema60":0.008636,"align":"역배열","vsEma24":-0.34,"isStock":false},{"symbol":"HOOKUSDT","price":0.0078,"change24h":-15.22,"rsi":41.7,"ema7":0.007893,"ema24":0.008155,"ema60":0.008659,"align":"역배열","vsEma24":-4.36,"isStock":false},{"symbol":"MOVEUSDT","price":0.0113,"change24h":-3.42,"rsi":50,"ema7":0.011199,"ema24":0.011273,"ema60":0.011512,"align":"역배열","vsEma24":0.24,"isStock":false},{"symbol":"VANAUSDT","price":1.086,"change24h":-3.38,"rsi":40.7,"ema7":1.084435,"ema24":1.095472,"ema60":1.115821,"align":"역배열","vsEma24":-0.86,"isStock":false},{"symbol":"GPSUSDT","price":0.009,"change24h":1.7,"rsi":54.2,"ema7":0.008932,"ema24":0.008925,"ema60":0.008932,"align":"혼조","vsEma24":0.84,"isStock":false},{"symbol":"SUSHIUSDT","price":0.1667,"change24h":-4.36,"rsi":43.6,"ema7":0.166068,"ema24":0.167792,"ema60":0.171398,"align":"역배열","vsEma24":-0.65,"isStock":false},{"symbol":"MEUSDT","price":0.0608,"change24h":-4.55,"rsi":40.6,"ema7":0.060791,"ema24":0.061652,"ema60":0.062598,"align":"역배열","vsEma24":-1.38,"isStock":false},{"symbol":"NXPCUSDT","price":0.3007,"change24h":-0.3,"rsi":48.8,"ema7":0.30164,"ema24":0.301215,"ema60":0.302748,"align":"혼조","vsEma24":-0.17,"isStock":false},{"symbol":"FXSUSDT","price":0.812,"change24h":-4.81,"rsi":39.4,"ema7":0.823024,"ema24":0.846003,"ema60":0.836154,"align":"혼조","vsEma24":-4.02,"isStock":false},{"symbol":"MKRUSDT","price":1813.7,"change24h":0.76,"rsi":45.2,"ema7":1814.336865,"ema24":1827.880651,"ema60":1811.693711,"align":"혼조","vsEma24":-0.78,"isStock":false},{"symbol":"NOTUSDT","price":0.000394,"change24h":-2.72,"rsi":42.7,"ema7":0.000392,"ema24":0.000398,"ema60":0.000404,"align":"역배열","vsEma24":-0.94,"isStock":false},{"symbol":"WAXPUSDT","price":0.00407,"change24h":-2.86,"rsi":40.9,"ema7":0.004098,"ema24":0.004125,"ema60":0.004197,"align":"역배열","vsEma24":-1.34,"isStock":false},{"symbol":"COMPUSDT","price":17.08,"change24h":-4.31,"rsi":36.2,"ema7":17.051956,"ema24":17.277235,"ema60":17.574425,"align":"역배열","vsEma24":-1.14,"isStock":false},{"symbol":"INITUSDT","price":0.0592,"change24h":0.34,"rsi":56.4,"ema7":0.058945,"ema24":0.058637,"ema60":0.058476,"align":"정배열","vsEma24":0.96,"isStock":false},{"symbol":"THETAUSDT","price":0.1465,"change24h":-3.62,"rsi":41.7,"ema7":0.146028,"ema24":0.147853,"ema60":0.150888,"align":"역배열","vsEma24":-0.91,"isStock":false},{"symbol":"1INCHUSDT","price":0.0708,"change24h":-2.21,"rsi":45.5,"ema7":0.07063,"ema24":0.071052,"ema60":0.071953,"align":"역배열","vsEma24":-0.36,"isStock":false},{"symbol":"OCEANUSDT","price":0.6123,"change24h":-1.19,"rsi":56.8,"ema7":0.609312,"ema24":0.601799,"ema60":0.605362,"align":"혼조","vsEma24":1.74,"isStock":false},{"symbol":"REZUSDT","price":0.003192,"change24h":-2.24,"rsi":45.6,"ema7":0.003183,"ema24":0.003212,"ema60":0.003242,"align":"역배열","vsEma24":-0.63,"isStock":false},{"symbol":"SXTUSDT","price":0.00755,"change24h":-2.2,"rsi":49,"ema7":0.007549,"ema24":0.007551,"ema60":0.007666,"align":"역배열","vsEma24":-0.01,"isStock":false},{"symbol":"COOKIEUSDT","price":0.0085,"change24h":-4.49,"rsi":36.3,"ema7":0.008539,"ema24":0.008678,"ema60":0.00887,"align":"역배열","vsEma24":-2.05,"isStock":false},{"symbol":"ONEUSDT","price":0.00131,"change24h":-5.75,"rsi":30.7,"ema7":0.001313,"ema24":0.001339,"ema60":0.001374,"align":"역배열","vsEma24":-2.15,"isStock":false},{"symbol":"CELRUSDT","price":0.001933,"change24h":-4.21,"rsi":35,"ema7":0.001932,"ema24":0.00196,"ema60":0.002008,"align":"역배열","vsEma24":-1.38,"isStock":false},{"symbol":"C98USDT","price":0.0134,"change24h":-3.6,"rsi":45.1,"ema7":0.013334,"ema24":0.013482,"ema60":0.013759,"align":"역배열","vsEma24":-0.61,"isStock":false},{"symbol":"TURBOUSDT","price":0.000866,"change24h":-2.48,"rsi":51.2,"ema7":0.000859,"ema24":0.000863,"ema60":0.000873,"align":"역배열","vsEma24":0.32,"isStock":false},{"symbol":"XTZUSDT","price":0.2218,"change24h":-3.44,"rsi":39.8,"ema7":0.221552,"ema24":0.223891,"ema60":0.228198,"align":"역배열","vsEma24":-0.93,"isStock":false},{"symbol":"ANIMEUSDT","price":0.00266,"change24h":-4.32,"rsi":40.9,"ema7":0.002655,"ema24":0.002689,"ema60":0.002776,"align":"역배열","vsEma24":-1.07,"isStock":false},{"symbol":"MANTAUSDT","price":0.07861,"change24h":-0.24,"rsi":50.4,"ema7":0.078419,"ema24":0.078527,"ema60":0.079163,"align":"역배열","vsEma24":0.11,"isStock":false},{"symbol":"LISTAUSDT","price":0.0503,"change24h":-5.09,"rsi":35.1,"ema7":0.050598,"ema24":0.051459,"ema60":0.052544,"align":"역배열","vsEma24":-2.25,"isStock":false},{"symbol":"MASKUSDT","price":0.385,"change24h":-1.53,"rsi":45.2,"ema7":0.384388,"ema24":0.38736,"ema60":0.391209,"align":"역배열","vsEma24":-0.61,"isStock":false},{"symbol":"BATUSDT","price":0.0898,"change24h":-0.33,"rsi":54.4,"ema7":0.089376,"ema24":0.089184,"ema60":0.089537,"align":"혼조","vsEma24":0.69,"isStock":false},{"symbol":"GASUSDT","price":1.054,"change24h":-2.5,"rsi":43,"ema7":1.051107,"ema24":1.061184,"ema60":1.078694,"align":"역배열","vsEma24":-0.68,"isStock":false},{"symbol":"CATIUSDT","price":0.0616,"change24h":2.33,"rsi":49.6,"ema7":0.061731,"ema24":0.061654,"ema60":0.061498,"align":"정배열","vsEma24":-0.09,"isStock":false},{"symbol":"RVNUSDT","price":0.00398,"change24h":-1.24,"rsi":45.5,"ema7":0.003976,"ema24":0.003994,"ema60":0.004053,"align":"역배열","vsEma24":-0.35,"isStock":false},{"symbol":"KSMUSDT","price":3.38,"change24h":-1.46,"rsi":52.8,"ema7":3.343494,"ema24":3.358066,"ema60":3.415855,"align":"역배열","vsEma24":0.65,"isStock":false},{"symbol":"LUNAUSDT","price":0.0495,"change24h":-3.7,"rsi":35.9,"ema7":0.049464,"ema24":0.050065,"ema60":0.050873,"align":"역배열","vsEma24":-1.13,"isStock":false},{"symbol":"ASTRUSDT","price":0.005281,"change24h":-0.75,"rsi":52.3,"ema7":0.00524,"ema24":0.005258,"ema60":0.00534,"align":"역배열","vsEma24":0.45,"isStock":false},{"symbol":"SHELLUSDT","price":0.0227,"change24h":-4.22,"rsi":40.6,"ema7":0.02265,"ema24":0.023016,"ema60":0.023624,"align":"역배열","vsEma24":-1.37,"isStock":false},{"symbol":"AUDIOUSDT","price":0.01417,"change24h":-2.88,"rsi":40.4,"ema7":0.014192,"ema24":0.014307,"ema60":0.014517,"align":"역배열","vsEma24":-0.96,"isStock":false},{"symbol":"MAGICUSDT","price":0.0439,"change24h":-4.15,"rsi":39.7,"ema7":0.043865,"ema24":0.044382,"ema60":0.045247,"align":"역배열","vsEma24":-1.09,"isStock":false},{"symbol":"COTIUSDT","price":0.00894,"change24h":-5.5,"rsi":35.5,"ema7":0.00894,"ema24":0.00909,"ema60":0.009287,"align":"역배열","vsEma24":-1.65,"isStock":false},{"symbol":"SKLUSDT","price":0.00384,"change24h":-3.76,"rsi":39.3,"ema7":0.003841,"ema24":0.003881,"ema60":0.003959,"align":"역배열","vsEma24":-1.07,"isStock":false},{"symbol":"HUMAUSDT","price":0.02225,"change24h":-4.63,"rsi":31.1,"ema7":0.022299,"ema24":0.02257,"ema60":0.022982,"align":"역배열","vsEma24":-1.42,"isStock":false},{"symbol":"ONTUSDT","price":0.04404,"change24h":-2.89,"rsi":41.5,"ema7":0.043888,"ema24":0.04432,"ema60":0.045045,"align":"역배열","vsEma24":-0.63,"isStock":false},{"symbol":"PROMUSDT","price":1.049,"change24h":-4.98,"rsi":35,"ema7":1.048419,"ema24":1.064856,"ema60":1.099012,"align":"역배열","vsEma24":-1.49,"isStock":false},{"symbol":"FLMUSDT","price":0.0167,"change24h":8.44,"rsi":44.1,"ema7":0.016281,"ema24":0.017164,"ema60":0.018625,"align":"역배열","vsEma24":-2.7,"isStock":false},{"symbol":"CHRUSDT","price":0.01454,"change24h":-4.59,"rsi":42.3,"ema7":0.014478,"ema24":0.01471,"ema60":0.015122,"align":"역배열","vsEma24":-1.16,"isStock":false},{"symbol":"SOPHUSDT","price":0.00529,"change24h":-0.56,"rsi":59.1,"ema7":0.005216,"ema24":0.005208,"ema60":0.005264,"align":"혼조","vsEma24":1.58,"isStock":false},{"symbol":"USUALUSDT","price":0.00957,"change24h":-4.49,"rsi":39.5,"ema7":0.009568,"ema24":0.009695,"ema60":0.009878,"align":"역배열","vsEma24":-1.29,"isStock":false},{"symbol":"EGLDUSDT","price":2.69,"change24h":-3.93,"rsi":40.4,"ema7":2.68337,"ema24":2.718081,"ema60":2.776634,"align":"역배열","vsEma24":-1.03,"isStock":false},{"symbol":"ARPAUSDT","price":0.00845,"change24h":-3.98,"rsi":43.9,"ema7":0.008439,"ema24":0.008517,"ema60":0.008596,"align":"역배열","vsEma24":-0.79,"isStock":false},{"symbol":"BALUSDT","price":0.967,"change24h":-3.68,"rsi":50.3,"ema7":0.959118,"ema24":0.967689,"ema60":0.93578,"align":"혼조","vsEma24":-0.07,"isStock":false},{"symbol":"AEVOUSDT","price":0.01877,"change24h":-1.26,"rsi":51.9,"ema7":0.01867,"ema24":0.01869,"ema60":0.018924,"align":"역배열","vsEma24":0.43,"isStock":false},{"symbol":"BBUSDT","price":0.0209,"change24h":-4.57,"rsi":37.1,"ema7":0.020908,"ema24":0.021242,"ema60":0.021723,"align":"역배열","vsEma24":-1.61,"isStock":false},{"symbol":"ANKRUSDT","price":0.00357,"change24h":-1.92,"rsi":45.9,"ema7":0.00356,"ema24":0.003581,"ema60":0.003632,"align":"역배열","vsEma24":-0.31,"isStock":false},{"symbol":"FLOWUSDT","price":0.02781,"change24h":-1.28,"rsi":48.4,"ema7":0.027669,"ema24":0.027821,"ema60":0.028144,"align":"역배열","vsEma24":-0.04,"isStock":false},{"symbol":"METISUSDT","price":3.05,"change24h":0.33,"rsi":51.6,"ema7":3.045022,"ema24":3.035596,"ema60":3.088188,"align":"혼조","vsEma24":0.47,"isStock":false},{"symbol":"TWTUSDT","price":0.3649,"change24h":-3.97,"rsi":39.7,"ema7":0.363463,"ema24":0.367933,"ema60":0.375325,"align":"역배열","vsEma24":-0.82,"isStock":false},{"symbol":"HAEDALUSDT","price":0.01675,"change24h":-3.68,"rsi":39.3,"ema7":0.016768,"ema24":0.016952,"ema60":0.017328,"align":"역배열","vsEma24":-1.19,"isStock":false},{"symbol":"YFIUSDT","price":1740,"change24h":-3.87,"rsi":38.1,"ema7":1738.920769,"ema24":1760.095637,"ema60":1792.592879,"align":"역배열","vsEma24":-1.14,"isStock":false},{"symbol":"MAVUSDT","price":0.0099,"change24h":-2.85,"rsi":45.1,"ema7":0.009858,"ema24":0.00995,"ema60":0.010155,"align":"역배열","vsEma24":-0.5,"isStock":false},{"symbol":"NKNUSDT","price":0.0073,"change24h":2.82,"rsi":45,"ema7":0.007254,"ema24":0.00754,"ema60":0.008195,"align":"역배열","vsEma24":-3.18,"isStock":false},{"symbol":"GTCUSDT","price":0.073,"change24h":-3.95,"rsi":44.4,"ema7":0.072466,"ema24":0.073664,"ema60":0.07513,"align":"역배열","vsEma24":-0.9,"isStock":false},{"symbol":"UMAUSDT","price":0.393,"change24h":-3.44,"rsi":29.5,"ema7":0.396026,"ema24":0.400787,"ema60":0.407075,"align":"역배열","vsEma24":-1.94,"isStock":false},{"symbol":"HOTUSDT","price":0.000297,"change24h":-2.62,"rsi":41.6,"ema7":0.000297,"ema24":0.000299,"ema60":0.000303,"align":"역배열","vsEma24":-0.79,"isStock":false},{"symbol":"XECUSDT","price":0.000005,"change24h":-3.34,"rsi":42,"ema7":0.000005,"ema24":0.000005,"ema60":0.000005,"align":"역배열","vsEma24":-0.64,"isStock":false},{"symbol":"SLPUSDT","price":0.000477,"change24h":-3.83,"rsi":37.1,"ema7":0.000477,"ema24":0.000483,"ema60":0.000494,"align":"역배열","vsEma24":-1.32,"isStock":false},{"symbol":"CELOUSDT","price":0.06133,"change24h":-2.46,"rsi":41.6,"ema7":0.06132,"ema24":0.061893,"ema60":0.063003,"align":"역배열","vsEma24":-0.91,"isStock":false},{"symbol":"COWUSDT","price":0.1538,"change24h":-2.35,"rsi":45.2,"ema7":0.153152,"ema24":0.154353,"ema60":0.156583,"align":"역배열","vsEma24":-0.36,"isStock":false},{"symbol":"KNCUSDT","price":0.112,"change24h":-3.11,"rsi":40.6,"ema7":0.111847,"ema24":0.112861,"ema60":0.114832,"align":"역배열","vsEma24":-0.76,"isStock":false},{"symbol":"ZRXUSDT","price":0.0815,"change24h":-1.81,"rsi":47.8,"ema7":0.081173,"ema24":0.081622,"ema60":0.08282,"align":"역배열","vsEma24":-0.15,"isStock":false},{"symbol":"SSVUSDT","price":2.218,"change24h":-3.06,"rsi":42.7,"ema7":2.218145,"ema24":2.238953,"ema60":2.280698,"align":"역배열","vsEma24":-0.94,"isStock":false},{"symbol":"BIGTIMEUSDT","price":0.00794,"change24h":-4.68,"rsi":36.8,"ema7":0.007962,"ema24":0.00807,"ema60":0.008278,"align":"역배열","vsEma24":-1.61,"isStock":false},{"symbol":"SFPUSDT","price":0.2234,"change24h":-3.66,"rsi":38.5,"ema7":0.223169,"ema24":0.225764,"ema60":0.229549,"align":"역배열","vsEma24":-1.05,"isStock":false},{"symbol":"IOTXUSDT","price":0.00296,"change24h":-3.58,"rsi":38.5,"ema7":0.002957,"ema24":0.002998,"ema60":0.00305,"align":"역배열","vsEma24":-1.26,"isStock":false},{"symbol":"AGLDUSDT","price":0.15,"change24h":-2.66,"rsi":48,"ema7":0.149149,"ema24":0.150082,"ema60":0.153104,"align":"역배열","vsEma24":-0.05,"isStock":false},{"symbol":"ICXUSDT","price":0.0263,"change24h":-4.01,"rsi":35.8,"ema7":0.026336,"ema24":0.026648,"ema60":0.027157,"align":"역배열","vsEma24":-1.31,"isStock":false},{"symbol":"BANDUSDT","price":0.152,"change24h":-5.59,"rsi":33.8,"ema7":0.152132,"ema24":0.15458,"ema60":0.157885,"align":"역배열","vsEma24":-1.67,"isStock":false},{"symbol":"GMXUSDT","price":5.57,"change24h":-4.79,"rsi":34.5,"ema7":5.578892,"ema24":5.645135,"ema60":5.761618,"align":"역배열","vsEma24":-1.33,"isStock":false},{"symbol":"QTUMUSDT","price":0.693,"change24h":-2.26,"rsi":47.1,"ema7":0.688169,"ema24":0.694111,"ema60":0.706523,"align":"역배열","vsEma24":-0.16,"isStock":false},{"symbol":"WOOUSDT","price":0.01207,"change24h":-4.13,"rsi":41.5,"ema7":0.012053,"ema24":0.012194,"ema60":0.01245,"align":"역배열","vsEma24":-1.01,"isStock":false},{"symbol":"REIUSDT","price":0.00401,"change24h":0.75,"rsi":32.7,"ema7":0.004052,"ema24":0.004236,"ema60":0.004599,"align":"역배열","vsEma24":-5.34,"isStock":false},{"symbol":"CTKUSDT","price":0.1119,"change24h":-4.03,"rsi":37,"ema7":0.11196,"ema24":0.113472,"ema60":0.116058,"align":"역배열","vsEma24":-1.38,"isStock":false},{"symbol":"CTSIUSDT","price":0.02273,"change24h":-3.19,"rsi":42.2,"ema7":0.022721,"ema24":0.022911,"ema60":0.02325,"align":"역배열","vsEma24":-0.79,"isStock":false},{"symbol":"MTLUSDT","price":0.235,"change24h":-3.69,"rsi":36.1,"ema7":0.234764,"ema24":0.23723,"ema60":0.241214,"align":"역배열","vsEma24":-0.94,"isStock":false}],"btc":{"price":62624.01,"change24h":-2.429,"rsi":40.98549297822106,"emaState":"역배열","priceState":"혼합","volState":"저조","verdict":"약세","ma50":{"side":"아래","pct":-12.438213784030017},"ma200":{"side":"아래","pct":-18.127905700860136}},"trend":{"total":226,"bull":9,"bear":54,"weakBull":25,"rsiL3":183,"rsiL5":184,"rsiL8":148,"up7d":{"up":31,"total":226},"series":[{"bull":75,"weak":79,"rsiL3":177,"rsiL5":132,"rsiL8":198,"total":226},{"bull":46,"weak":51,"rsiL3":39,"rsiL5":71,"rsiL8":165,"total":226},{"bull":65,"weak":72,"rsiL3":111,"rsiL5":162,"rsiL8":184,"total":226},{"bull":103,"weak":114,"rsiL3":185,"rsiL5":164,"rsiL8":183,"total":226},{"bull":126,"weak":136,"rsiL3":200,"rsiL5":184,"rsiL8":177,"total":226},{"bull":80,"weak":86,"rsiL3":152,"rsiL5":137,"rsiL8":170,"total":226},{"bull":83,"weak":95,"rsiL3":57,"rsiL5":176,"rsiL8":109,"total":226},{"bull":44,"weak":54,"rsiL3":30,"rsiL5":105,"rsiL8":100,"total":226},{"bull":41,"weak":48,"rsiL3":62,"rsiL5":44,"rsiL8":90,"total":226},{"bull":39,"weak":47,"rsiL3":56,"rsiL5":36,"rsiL8":129,"total":226},{"bull":14,"weak":20,"rsiL3":29,"rsiL5":25,"rsiL8":38,"total":226},{"bull":19,"weak":25,"rsiL3":35,"rsiL5":31,"rsiL8":27,"total":226},{"bull":17,"weak":25,"rsiL3":32,"rsiL5":33,"rsiL8":24,"total":226},{"bull":17,"weak":22,"rsiL3":98,"rsiL5":35,"rsiL8":31,"total":226},{"bull":32,"weak":40,"rsiL3":169,"rsiL5":84,"rsiL8":53,"total":226},{"bull":30,"weak":41,"rsiL3":171,"rsiL5":176,"rsiL8":67,"total":226},{"bull":30,"weak":39,"rsiL3":175,"rsiL5":138,"rsiL8":71,"total":226},{"bull":70,"weak":85,"rsiL3":199,"rsiL5":199,"rsiL8":186,"total":226},{"bull":87,"weak":108,"rsiL3":194,"rsiL5":203,"rsiL8":194,"total":226},{"bull":110,"weak":139,"rsiL3":205,"rsiL5":195,"rsiL8":193,"total":226},{"bull":67,"weak":85,"rsiL3":36,"rsiL5":168,"rsiL8":180,"total":226},{"bull":9,"weak":11,"rsiL3":13,"rsiL5":33,"rsiL8":72,"total":226},{"bull":21,"weak":24,"rsiL3":26,"rsiL5":27,"rsiL8":72,"total":226},{"bull":11,"weak":12,"rsiL3":18,"rsiL5":19,"rsiL8":40,"total":226},{"bull":20,"weak":22,"rsiL3":162,"rsiL5":19,"rsiL8":66,"total":226},{"bull":23,"weak":29,"rsiL3":110,"rsiL5":35,"rsiL8":29,"total":226},{"bull":22,"weak":32,"rsiL3":188,"rsiL5":188,"rsiL8":37,"total":226},{"bull":23,"weak":31,"rsiL3":169,"rsiL5":116,"rsiL8":29,"total":226},{"bull":36,"weak":45,"rsiL3":156,"rsiL5":198,"rsiL8":57,"total":226},{"bull":17,"weak":23,"rsiL3":46,"rsiL5":80,"rsiL8":142,"total":226},{"bull":8,"weak":11,"rsiL3":21,"rsiL5":29,"rsiL8":29,"total":226},{"bull":13,"weak":15,"rsiL3":20,"rsiL5":34,"rsiL8":60,"total":226},{"bull":19,"weak":21,"rsiL3":81,"rsiL5":41,"rsiL8":71,"total":226},{"bull":20,"weak":22,"rsiL3":190,"rsiL5":45,"rsiL8":87,"total":226},{"bull":22,"weak":25,"rsiL3":186,"rsiL5":148,"rsiL8":83,"total":226},{"bull":22,"weak":26,"rsiL3":152,"rsiL5":188,"rsiL8":76,"total":226},{"bull":25,"weak":30,"rsiL3":82,"rsiL5":169,"rsiL8":43,"total":226},{"bull":9,"weak":12,"rsiL3":29,"rsiL5":69,"rsiL8":59,"total":226},{"bull":15,"weak":20,"rsiL3":78,"rsiL5":89,"rsiL8":165,"total":226},{"bull":9,"weak":17,"rsiL3":48,"rsiL5":40,"rsiL8":111,"total":226},{"bull":10,"weak":21,"rsiL3":159,"rsiL5":80,"rsiL8":121,"total":226},{"bull":4,"weak":7,"rsiL3":13,"rsiL5":18,"rsiL8":22,"total":226},{"bull":7,"weak":9,"rsiL3":56,"rsiL5":64,"rsiL8":25,"total":226},{"bull":5,"weak":8,"rsiL3":22,"rsiL5":18,"rsiL8":22,"total":226},{"bull":5,"weak":11,"rsiL3":202,"rsiL5":88,"rsiL8":46,"total":226},{"bull":5,"weak":11,"rsiL3":194,"rsiL5":96,"rsiL8":153,"total":226},{"bull":8,"weak":15,"rsiL3":211,"rsiL5":209,"rsiL8":142,"total":226},{"bull":12,"weak":21,"rsiL3":204,"rsiL5":198,"rsiL8":177,"total":226},{"bull":13,"weak":23,"rsiL3":174,"rsiL5":204,"rsiL8":139,"total":226},{"bull":19,"weak":32,"rsiL3":141,"rsiL5":203,"rsiL8":211,"total":226},{"bull":24,"weak":44,"rsiL3":188,"rsiL5":202,"rsiL8":206,"total":226},{"bull":25,"weak":47,"rsiL3":182,"rsiL5":166,"rsiL8":208,"total":226},{"bull":18,"weak":47,"rsiL3":135,"rsiL5":176,"rsiL8":200,"total":226},{"bull":12,"weak":22,"rsiL3":34,"rsiL5":76,"rsiL8":138,"total":226},{"bull":4,"weak":6,"rsiL3":11,"rsiL5":20,"rsiL8":28,"total":226},{"bull":7,"weak":15,"rsiL3":24,"rsiL5":36,"rsiL8":90,"total":226},{"bull":10,"weak":17,"rsiL3":122,"rsiL5":39,"rsiL8":90,"total":226},{"bull":10,"weak":14,"rsiL3":170,"rsiL5":30,"rsiL8":52,"total":226},{"bull":15,"weak":24,"rsiL3":122,"rsiL5":123,"rsiL8":62,"total":226},{"bull":8,"weak":17,"rsiL3":57,"rsiL5":164,"rsiL8":34,"total":226},{"bull":9,"weak":20,"rsiL3":149,"rsiL5":115,"rsiL8":62,"total":226},{"bull":10,"weak":19,"rsiL3":97,"rsiL5":98,"rsiL8":111,"total":226},{"bull":12,"weak":25,"rsiL3":187,"rsiL5":187,"rsiL8":196,"total":226},{"bull":15,"weak":41,"rsiL3":202,"rsiL5":197,"rsiL8":201,"total":226},{"bull":14,"weak":44,"rsiL3":198,"rsiL5":195,"rsiL8":190,"total":226},{"bull":12,"weak":52,"rsiL3":178,"rsiL5":187,"rsiL8":194,"total":226},{"bull":13,"weak":50,"rsiL3":54,"rsiL5":185,"rsiL8":172,"total":226},{"bull":15,"weak":68,"rsiL3":154,"rsiL5":181,"rsiL8":195,"total":226},{"bull":19,"weak":48,"rsiL3":66,"rsiL5":50,"rsiL8":169,"total":226},{"bull":16,"weak":36,"rsiL3":68,"rsiL5":60,"rsiL8":166,"total":226},{"bull":19,"weak":57,"rsiL3":59,"rsiL5":94,"rsiL8":151,"total":226},{"bull":19,"weak":35,"rsiL3":61,"rsiL5":74,"rsiL8":32,"total":226},{"bull":17,"weak":46,"rsiL3":154,"rsiL5":64,"rsiL8":85,"total":226},{"bull":21,"weak":64,"rsiL3":159,"rsiL5":164,"rsiL8":121,"total":226},{"bull":13,"weak":54,"rsiL3":157,"rsiL5":154,"rsiL8":124,"total":226},{"bull":17,"weak":59,"rsiL3":117,"rsiL5":103,"rsiL8":81,"total":226},{"bull":15,"weak":32,"rsiL3":36,"rsiL5":98,"rsiL8":80,"total":226},{"bull":16,"weak":45,"rsiL3":64,"rsiL5":83,"rsiL8":113,"total":226},{"bull":21,"weak":60,"rsiL3":123,"rsiL5":91,"rsiL8":115,"total":226},{"bull":24,"weak":70,"rsiL3":193,"rsiL5":153,"rsiL8":174,"total":226},{"bull":27,"weak":92,"rsiL3":187,"rsiL5":171,"rsiL8":165,"total":226},{"bull":20,"weak":78,"rsiL3":124,"rsiL5":167,"rsiL8":118,"total":226},{"bull":29,"weak":94,"rsiL3":110,"rsiL5":171,"rsiL8":138,"total":226},{"bull":34,"weak":131,"rsiL3":115,"rsiL5":172,"rsiL8":165,"total":226},{"bull":32,"weak":113,"rsiL3":154,"rsiL5":127,"rsiL8":178,"total":226},{"bull":32,"weak":90,"rsiL3":115,"rsiL5":79,"rsiL8":157,"total":226},{"bull":18,"weak":64,"rsiL3":37,"rsiL5":100,"rsiL8":118,"total":226},{"bull":13,"weak":39,"rsiL3":41,"rsiL5":51,"rsiL8":70,"total":226},{"bull":35,"weak":107,"rsiL3":124,"rsiL5":87,"rsiL8":101,"total":226},{"bull":47,"weak":124,"rsiL3":177,"rsiL5":157,"rsiL8":167,"total":226},{"bull":50,"weak":120,"rsiL3":193,"rsiL5":137,"rsiL8":142,"total":226},{"bull":39,"weak":81,"rsiL3":77,"rsiL5":121,"rsiL8":74,"total":226},{"bull":43,"weak":84,"rsiL3":62,"rsiL5":162,"rsiL8":93,"total":226},{"bull":44,"weak":86,"rsiL3":72,"rsiL5":85,"rsiL8":105,"total":226},{"bull":25,"weak":59,"rsiL3":120,"rsiL5":49,"rsiL8":108,"total":226},{"bull":53,"weak":103,"rsiL3":143,"rsiL5":94,"rsiL8":179,"total":226},{"bull":52,"weak":121,"rsiL3":161,"rsiL5":160,"rsiL8":149,"total":226},{"bull":46,"weak":116,"rsiL3":161,"rsiL5":141,"rsiL8":104,"total":226},{"bull":65,"weak":131,"rsiL3":158,"rsiL5":156,"rsiL8":136,"total":226},{"bull":78,"weak":147,"rsiL3":117,"rsiL5":171,"rsiL8":155,"total":226},{"bull":71,"weak":114,"rsiL3":107,"rsiL5":129,"rsiL8":143,"total":226},{"bull":48,"weak":95,"rsiL3":88,"rsiL5":78,"rsiL8":134,"total":226},{"bull":28,"weak":50,"rsiL3":39,"rsiL5":49,"rsiL8":109,"total":226},{"bull":27,"weak":36,"rsiL3":41,"rsiL5":36,"rsiL8":61,"total":226},{"bull":47,"weak":73,"rsiL3":59,"rsiL5":51,"rsiL8":59,"total":226},{"bull":52,"weak":83,"rsiL3":126,"rsiL5":81,"rsiL8":81,"total":226},{"bull":45,"weak":67,"rsiL3":136,"rsiL5":74,"rsiL8":61,"total":226},{"bull":74,"weak":106,"rsiL3":158,"rsiL5":134,"rsiL8":81,"total":226},{"bull":58,"weak":90,"rsiL3":113,"rsiL5":155,"rsiL8":88,"total":226},{"bull":31,"weak":42,"rsiL3":73,"rsiL5":70,"rsiL8":55,"total":226},{"bull":55,"weak":78,"rsiL3":74,"rsiL5":99,"rsiL8":116,"total":226},{"bull":54,"weak":81,"rsiL3":91,"rsiL5":120,"rsiL8":134,"total":226},{"bull":50,"weak":74,"rsiL3":147,"rsiL5":74,"rsiL8":114,"total":226},{"bull":53,"weak":86,"rsiL3":120,"rsiL5":111,"rsiL8":111,"total":226},{"bull":42,"weak":56,"rsiL3":80,"rsiL5":127,"rsiL8":96,"total":226},{"bull":34,"weak":46,"rsiL3":67,"rsiL5":62,"rsiL8":59,"total":226},{"bull":46,"weak":61,"rsiL3":68,"rsiL5":80,"rsiL8":71,"total":226},{"bull":42,"weak":56,"rsiL3":117,"rsiL5":95,"rsiL8":121,"total":226},{"bull":13,"weak":16,"rsiL3":45,"rsiL5":26,"rsiL8":28,"total":226},{"bull":12,"weak":12,"rsiL3":30,"rsiL5":29,"rsiL8":19,"total":226},{"bull":11,"weak":12,"rsiL3":27,"rsiL5":33,"rsiL8":26,"total":226},{"bull":10,"weak":11,"rsiL3":21,"rsiL5":20,"rsiL8":22,"total":226},{"bull":24,"weak":27,"rsiL3":188,"rsiL5":70,"rsiL8":76,"total":226},{"bull":41,"weak":50,"rsiL3":203,"rsiL5":189,"rsiL8":159,"total":226},{"bull":35,"weak":47,"rsiL3":205,"rsiL5":192,"rsiL8":92,"total":226},{"bull":26,"weak":35,"rsiL3":90,"rsiL5":181,"rsiL8":65,"total":226},{"bull":37,"weak":54,"rsiL3":44,"rsiL5":201,"rsiL8":162,"total":226},{"bull":36,"weak":54,"rsiL3":102,"rsiL5":136,"rsiL8":184,"total":226},{"bull":30,"weak":40,"rsiL3":150,"rsiL5":47,"rsiL8":184,"total":226},{"bull":40,"weak":53,"rsiL3":142,"rsiL5":133,"rsiL8":202,"total":226},{"bull":44,"weak":64,"rsiL3":128,"rsiL5":168,"rsiL8":156,"total":226},{"bull":39,"weak":56,"rsiL3":128,"rsiL5":107,"rsiL8":62,"total":226},{"bull":35,"weak":53,"rsiL3":86,"rsiL5":105,"rsiL8":105,"total":226},{"bull":70,"weak":109,"rsiL3":191,"rsiL5":193,"rsiL8":189,"total":226},{"bull":78,"weak":142,"rsiL3":188,"rsiL5":183,"rsiL8":181,"total":226},{"bull":88,"weak":160,"rsiL3":196,"rsiL5":190,"rsiL8":188,"total":226},{"bull":50,"weak":77,"rsiL3":53,"rsiL5":152,"rsiL8":161,"total":226},{"bull":21,"weak":29,"rsiL3":18,"rsiL5":114,"rsiL8":91,"total":226},{"bull":30,"weak":41,"rsiL3":22,"rsiL5":33,"rsiL8":104,"total":226},{"bull":22,"weak":28,"rsiL3":38,"rsiL5":24,"rsiL8":96,"total":226},{"bull":13,"weak":16,"rsiL3":32,"rsiL5":16,"rsiL8":35,"total":226},{"bull":11,"weak":16,"rsiL3":22,"rsiL5":24,"rsiL8":18,"total":226},{"bull":16,"weak":19,"rsiL3":48,"rsiL5":43,"rsiL8":18,"total":226},{"bull":14,"weak":16,"rsiL3":68,"rsiL5":26,"rsiL8":18,"total":226},{"bull":9,"weak":10,"rsiL3":35,"rsiL5":26,"rsiL8":17,"total":226},{"bull":13,"weak":16,"rsiL3":47,"rsiL5":54,"rsiL8":27,"total":226},{"bull":16,"weak":21,"rsiL3":131,"rsiL5":99,"rsiL8":47,"total":226},{"bull":18,"weak":25,"rsiL3":171,"rsiL5":85,"rsiL8":49,"total":226},{"bull":21,"weak":28,"rsiL3":161,"rsiL5":127,"rsiL8":94,"total":226},{"bull":20,"weak":25,"rsiL3":133,"rsiL5":191,"rsiL8":132,"total":226},{"bull":14,"weak":16,"rsiL3":93,"rsiL5":120,"rsiL8":76,"total":226},{"bull":15,"weak":19,"rsiL3":59,"rsiL5":75,"rsiL8":84,"total":226},{"bull":11,"weak":15,"rsiL3":18,"rsiL5":27,"rsiL8":51,"total":226},{"bull":5,"weak":9,"rsiL3":20,"rsiL5":21,"rsiL8":39,"total":226},{"bull":4,"weak":8,"rsiL3":12,"rsiL5":15,"rsiL8":18,"total":226},{"bull":5,"weak":7,"rsiL3":51,"rsiL5":20,"rsiL8":22,"total":226},{"bull":3,"weak":6,"rsiL3":59,"rsiL5":20,"rsiL8":18,"total":226},{"bull":10,"weak":12,"rsiL3":194,"rsiL5":152,"rsiL8":29,"total":226},{"bull":5,"weak":9,"rsiL3":173,"rsiL5":153,"rsiL8":33,"total":226},{"bull":4,"weak":12,"rsiL3":201,"rsiL5":198,"rsiL8":124,"total":226},{"bull":5,"weak":14,"rsiL3":163,"rsiL5":184,"rsiL8":179,"total":226},{"bull":6,"weak":11,"rsiL3":166,"rsiL5":185,"rsiL8":173,"total":226},{"bull":6,"weak":12,"rsiL3":62,"rsiL5":152,"rsiL8":191,"total":226},{"bull":4,"weak":12,"rsiL3":77,"rsiL5":155,"rsiL8":180,"total":226},{"bull":9,"weak":17,"rsiL3":122,"rsiL5":70,"rsiL8":189,"total":226},{"bull":13,"weak":19,"rsiL3":154,"rsiL5":144,"rsiL8":173,"total":226},{"bull":11,"weak":22,"rsiL3":187,"rsiL5":175,"rsiL8":186,"total":226},{"bull":9,"weak":25,"rsiL3":183,"rsiL5":184,"rsiL8":148,"total":226}]},"moneyflow":{"ethbtc":{"value":0.02662,"change24h":-1.18,"chart24h":[0.026952,0.026995,0.026986,0.026975,0.026987,0.027002,0.02702,0.027026,0.026889,0.026763,0.026424,0.026464,0.026515,0.026571,0.026576,0.026616,0.026596,0.026562,0.026525,0.02657,0.026598,0.026649,0.026639,0.02662]},"usdtd":{"value":8.35,"change24h":0.21}},"history":[{"t":1782054165468,"ethbtc":0.026937,"usdtd":8.16,"bull":29,"weakBull":41,"bear":19,"rsiL3":54,"up7":64,"up7Total":99},{"t":1782061013135,"ethbtc":0.026938,"usdtd":8.16,"bull":24,"weakBull":31,"bear":26,"rsiL3":29,"up7":63,"up7Total":99},{"t":1782075642982,"ethbtc":0.026962,"usdtd":8.19,"bull":12,"weakBull":14,"bear":40,"rsiL3":13,"up7":40,"up7Total":99},{"t":1782093121805,"ethbtc":0.027015,"usdtd":8.11,"bull":27,"weakBull":30,"bear":8,"rsiL3":83,"up7":41,"up7Total":99},{"t":1782107005974,"ethbtc":0.027036,"usdtd":8.15,"bull":24,"weakBull":33,"bear":20,"rsiL3":51,"up7":36,"up7Total":99},{"t":1782109206628,"ethbtc":0.02709,"usdtd":8.14,"bull":22,"weakBull":30,"bear":27,"rsiL3":72,"up7":35,"up7Total":99},{"t":1782114584737,"ethbtc":0.027211,"usdtd":8.13,"bull":41,"weakBull":57,"bear":43,"rsiL3":148,"up7":68,"up7Total":226},{"t":1782117172454,"ethbtc":0.027204,"usdtd":8.13,"bull":37,"weakBull":57,"bear":66,"rsiL3":121,"up7":65,"up7Total":226},{"t":1782117940733,"ethbtc":0.027239,"usdtd":8.15,"bull":43,"weakBull":63,"bear":53,"rsiL3":145,"up7":68,"up7Total":226},{"t":1782118853923,"ethbtc":0.027236,"usdtd":8.14,"bull":42,"weakBull":64,"bear":66,"rsiL3":159,"up7":65,"up7Total":226},{"t":1782119743990,"ethbtc":0.027243,"usdtd":8.14,"bull":38,"weakBull":58,"bear":77,"rsiL3":148,"up7":65,"up7Total":226},{"t":1782120651655,"ethbtc":0.027239,"usdtd":8.15,"bull":28,"weakBull":46,"bear":90,"rsiL3":122,"up7":64,"up7Total":226},{"t":1782121540267,"ethbtc":0.02724,"usdtd":8.14,"bull":32,"weakBull":50,"bear":81,"rsiL3":130,"up7":65,"up7Total":226},{"t":1782122458166,"ethbtc":0.027214,"usdtd":8.15,"bull":37,"weakBull":53,"bear":89,"rsiL3":71,"up7":59,"up7Total":226},{"t":1782123344120,"ethbtc":0.027249,"usdtd":8.15,"bull":39,"weakBull":57,"bear":74,"rsiL3":89,"up7":58,"up7Total":226},{"t":1782124251273,"ethbtc":0.027233,"usdtd":8.15,"bull":38,"weakBull":53,"bear":79,"rsiL3":82,"up7":58,"up7Total":226},{"t":1782125145842,"ethbtc":0.027261,"usdtd":8.14,"bull":30,"weakBull":47,"bear":86,"rsiL3":78,"up7":60,"up7Total":226},{"t":1782126056740,"ethbtc":0.027264,"usdtd":8.14,"bull":38,"weakBull":62,"bear":81,"rsiL3":81,"up7":57,"up7Total":226},{"t":1782126940956,"ethbtc":0.027246,"usdtd":8.12,"bull":54,"weakBull":87,"bear":31,"rsiL3":167,"up7":59,"up7Total":226},{"t":1782127850659,"ethbtc":0.027232,"usdtd":8.13,"bull":55,"weakBull":89,"bear":28,"rsiL3":171,"up7":59,"up7Total":226},{"t":1782128747751,"ethbtc":0.027299,"usdtd":8.08,"bull":68,"weakBull":102,"bear":20,"rsiL3":190,"up7":62,"up7Total":226},{"t":1782129657039,"ethbtc":0.027334,"usdtd":8.09,"bull":74,"weakBull":128,"bear":20,"rsiL3":192,"up7":59,"up7Total":226},{"t":1782130544054,"ethbtc":0.027278,"usdtd":8.09,"bull":71,"weakBull":127,"bear":19,"rsiL3":191,"up7":58,"up7Total":226},{"t":1782131455126,"ethbtc":0.027187,"usdtd":8.07,"bull":68,"weakBull":128,"bear":20,"rsiL3":190,"up7":58,"up7Total":226},{"t":1782132340126,"ethbtc":0.027121,"usdtd":8.06,"bull":73,"weakBull":136,"bear":20,"rsiL3":190,"up7":56,"up7Total":226},{"t":1782133259931,"ethbtc":0.0271,"usdtd":8.05,"bull":80,"weakBull":156,"bear":18,"rsiL3":195,"up7":57,"up7Total":226},{"t":1782134145567,"ethbtc":0.027089,"usdtd":8.05,"bull":74,"weakBull":147,"bear":22,"rsiL3":188,"up7":56,"up7Total":226},{"t":1782135055499,"ethbtc":0.027154,"usdtd":8.05,"bull":74,"weakBull":145,"bear":23,"rsiL3":189,"up7":57,"up7Total":226},{"t":1782135943696,"ethbtc":0.027109,"usdtd":8.02,"bull":81,"weakBull":156,"bear":21,"rsiL3":194,"up7":59,"up7Total":226},{"t":1782136860554,"ethbtc":0.027106,"usdtd":8.01,"bull":99,"weakBull":164,"bear":20,"rsiL3":160,"up7":59,"up7Total":226},{"t":1782137746006,"ethbtc":0.02707,"usdtd":8.02,"bull":79,"weakBull":138,"bear":21,"rsiL3":108,"up7":53,"up7Total":226},{"t":1782138654271,"ethbtc":0.026999,"usdtd":8.06,"bull":49,"weakBull":84,"bear":34,"rsiL3":58,"up7":50,"up7Total":226},{"t":1782139545106,"ethbtc":0.027021,"usdtd":8.06,"bull":36,"weakBull":63,"bear":38,"rsiL3":45,"up7":47,"up7Total":226},{"t":1782140463712,"ethbtc":0.027006,"usdtd":8.07,"bull":54,"weakBull":87,"bear":40,"rsiL3":35,"up7":47,"up7Total":226},{"t":1782141347834,"ethbtc":0.026984,"usdtd":8.06,"bull":58,"weakBull":90,"bear":36,"rsiL3":33,"up7":46,"up7Total":226},{"t":1782142255289,"ethbtc":0.026962,"usdtd":8.07,"bull":50,"weakBull":79,"bear":40,"rsiL3":30,"up7":44,"up7Total":226},{"t":1782143142465,"ethbtc":0.026966,"usdtd":8.06,"bull":45,"weakBull":73,"bear":38,"rsiL3":27,"up7":45,"up7Total":226},{"t":1782144034914,"ethbtc":0.026901,"usdtd":8.09,"bull":19,"weakBull":31,"bear":62,"rsiL3":21,"up7":46,"up7Total":226},{"t":1782144945800,"ethbtc":0.026905,"usdtd":8.11,"bull":18,"weakBull":21,"bear":67,"rsiL3":20,"up7":44,"up7Total":226},{"t":1782145853354,"ethbtc":0.02693,"usdtd":8.11,"bull":25,"weakBull":32,"bear":67,"rsiL3":20,"up7":43,"up7Total":226},{"t":1782146741317,"ethbtc":0.026903,"usdtd":8.11,"bull":20,"weakBull":26,"bear":72,"rsiL3":18,"up7":42,"up7Total":226},{"t":1782147657286,"ethbtc":0.026894,"usdtd":8.1,"bull":28,"weakBull":41,"bear":67,"rsiL3":45,"up7":47,"up7Total":226},{"t":1782148539970,"ethbtc":0.026925,"usdtd":8.1,"bull":18,"weakBull":24,"bear":74,"rsiL3":34,"up7":45,"up7Total":226},{"t":1782149448836,"ethbtc":0.026899,"usdtd":8.12,"bull":11,"weakBull":15,"bear":80,"rsiL3":25,"up7":44,"up7Total":226},{"t":1782150342907,"ethbtc":0.02694,"usdtd":8.13,"bull":12,"weakBull":18,"bear":82,"rsiL3":31,"up7":44,"up7Total":226},{"t":1782151259572,"ethbtc":0.02695,"usdtd":8.11,"bull":20,"weakBull":29,"bear":88,"rsiL3":84,"up7":51,"up7Total":226},{"t":1782152139114,"ethbtc":0.02699,"usdtd":8.11,"bull":25,"weakBull":38,"bear":83,"rsiL3":104,"up7":53,"up7Total":226},{"t":1782153071670,"ethbtc":0.026968,"usdtd":8.11,"bull":16,"weakBull":21,"bear":87,"rsiL3":68,"up7":51,"up7Total":226},{"t":1782153946137,"ethbtc":0.026921,"usdtd":8.11,"bull":14,"weakBull":20,"bear":91,"rsiL3":56,"up7":49,"up7Total":226},{"t":1782154857143,"ethbtc":0.026929,"usdtd":8.13,"bull":9,"weakBull":12,"bear":112,"rsiL3":23,"up7":53,"up7Total":226},{"t":1782155747527,"ethbtc":0.026941,"usdtd":8.14,"bull":8,"weakBull":12,"bear":113,"rsiL3":24,"up7":52,"up7Total":226},{"t":1782156653716,"ethbtc":0.026907,"usdtd":8.14,"bull":8,"weakBull":13,"bear":113,"rsiL3":25,"up7":53,"up7Total":226},{"t":1782157540750,"ethbtc":0.026921,"usdtd":8.13,"bull":9,"weakBull":14,"bear":115,"rsiL3":23,"up7":53,"up7Total":226},{"t":1782158455445,"ethbtc":0.026901,"usdtd":8.13,"bull":9,"weakBull":14,"bear":120,"rsiL3":33,"up7":52,"up7Total":226},{"t":1782159343573,"ethbtc":0.026917,"usdtd":8.12,"bull":14,"weakBull":19,"bear":116,"rsiL3":49,"up7":51,"up7Total":226},{"t":1782160251527,"ethbtc":0.026915,"usdtd":8.14,"bull":14,"weakBull":18,"bear":119,"rsiL3":40,"up7":50,"up7Total":226},{"t":1782161137989,"ethbtc":0.026925,"usdtd":8.13,"bull":17,"weakBull":21,"bear":115,"rsiL3":44,"up7":50,"up7Total":226},{"t":1782162055687,"ethbtc":0.026924,"usdtd":8.13,"bull":16,"weakBull":19,"bear":117,"rsiL3":108,"up7":48,"up7Total":226},{"t":1782162942874,"ethbtc":0.026954,"usdtd":8.13,"bull":15,"weakBull":18,"bear":120,"rsiL3":99,"up7":47,"up7Total":226},{"t":1782163849763,"ethbtc":0.026963,"usdtd":8.14,"bull":15,"weakBull":19,"bear":126,"rsiL3":73,"up7":46,"up7Total":226},{"t":1782164737098,"ethbtc":0.026945,"usdtd":8.14,"bull":11,"weakBull":14,"bear":132,"rsiL3":55,"up7":45,"up7Total":226},{"t":1782165651417,"ethbtc":0.02694,"usdtd":8.15,"bull":15,"weakBull":19,"bear":133,"rsiL3":76,"up7":51,"up7Total":226},{"t":1782166537541,"ethbtc":0.026954,"usdtd":8.14,"bull":14,"weakBull":18,"bear":128,"rsiL3":108,"up7":52,"up7Total":226},{"t":1782167237708,"ethbtc":0.026922,"usdtd":8.14,"bull":10,"weakBull":12,"bear":141,"rsiL3":46,"up7":50,"up7Total":226},{"t":1782167452079,"ethbtc":0.026909,"usdtd":8.15,"bull":9,"weakBull":11,"bear":142,"rsiL3":30,"up7":48,"up7Total":226},{"t":1782168338034,"ethbtc":0.026928,"usdtd":8.17,"bull":10,"weakBull":12,"bear":143,"rsiL3":25,"up7":46,"up7Total":226},{"t":1782169252327,"ethbtc":0.026958,"usdtd":8.18,"bull":11,"weakBull":13,"bear":145,"rsiL3":26,"up7":45,"up7Total":226},{"t":1782170140836,"ethbtc":0.026949,"usdtd":8.18,"bull":9,"weakBull":11,"bear":145,"rsiL3":29,"up7":46,"up7Total":226},{"t":1782171046995,"ethbtc":0.026961,"usdtd":8.17,"bull":9,"weakBull":11,"bear":139,"rsiL3":37,"up7":47,"up7Total":226},{"t":1782171939253,"ethbtc":0.026985,"usdtd":8.17,"bull":12,"weakBull":14,"bear":140,"rsiL3":40,"up7":47,"up7Total":226},{"t":1782172854892,"ethbtc":0.026985,"usdtd":8.17,"bull":10,"weakBull":13,"bear":144,"rsiL3":55,"up7":47,"up7Total":226},{"t":1782173736585,"ethbtc":0.026982,"usdtd":8.17,"bull":11,"weakBull":16,"bear":142,"rsiL3":66,"up7":49,"up7Total":226},{"t":1782174646759,"ethbtc":0.026967,"usdtd":8.18,"bull":9,"weakBull":11,"bear":149,"rsiL3":42,"up7":45,"up7Total":226},{"t":1782175540098,"ethbtc":0.026973,"usdtd":8.17,"bull":11,"weakBull":16,"bear":126,"rsiL3":111,"up7":52,"up7Total":226},{"t":1782176450116,"ethbtc":0.026996,"usdtd":8.16,"bull":15,"weakBull":22,"bear":125,"rsiL3":187,"up7":52,"up7Total":226},{"t":1782177337742,"ethbtc":0.026983,"usdtd":8.15,"bull":17,"weakBull":23,"bear":124,"rsiL3":182,"up7":52,"up7Total":226},{"t":1782178246749,"ethbtc":0.027,"usdtd":8.15,"bull":19,"weakBull":25,"bear":113,"rsiL3":189,"up7":53,"up7Total":226},{"t":1782179142110,"ethbtc":0.02697,"usdtd":8.16,"bull":13,"weakBull":18,"bear":142,"rsiL3":152,"up7":49,"up7Total":226},{"t":1782180052761,"ethbtc":0.026983,"usdtd":8.16,"bull":16,"weakBull":24,"bear":136,"rsiL3":139,"up7":63,"up7Total":226},{"t":1782180939081,"ethbtc":0.026981,"usdtd":8.16,"bull":15,"weakBull":23,"bear":139,"rsiL3":127,"up7":58,"up7Total":226},{"t":1782181844898,"ethbtc":0.026967,"usdtd":8.15,"bull":14,"weakBull":20,"bear":138,"rsiL3":125,"up7":60,"up7Total":226},{"t":1782182738528,"ethbtc":0.026983,"usdtd":8.15,"bull":14,"weakBull":23,"bear":132,"rsiL3":136,"up7":60,"up7Total":226},{"t":1782183653993,"ethbtc":0.026996,"usdtd":8.14,"bull":18,"weakBull":24,"bear":118,"rsiL3":114,"up7":50,"up7Total":226},{"t":1782184537962,"ethbtc":0.026996,"usdtd":8.16,"bull":11,"weakBull":17,"bear":141,"rsiL3":82,"up7":50,"up7Total":226},{"t":1782185447311,"ethbtc":0.026988,"usdtd":8.16,"bull":18,"weakBull":24,"bear":117,"rsiL3":110,"up7":52,"up7Total":226},{"t":1782186344426,"ethbtc":0.027,"usdtd":8.17,"bull":15,"weakBull":20,"bear":126,"rsiL3":104,"up7":51,"up7Total":226},{"t":1782187250249,"ethbtc":0.027008,"usdtd":8.16,"bull":19,"weakBull":27,"bear":93,"rsiL3":157,"up7":58,"up7Total":226},{"t":1782188138431,"ethbtc":0.027016,"usdtd":8.16,"bull":19,"weakBull":24,"bear":99,"rsiL3":155,"up7":58,"up7Total":226},{"t":1782189047930,"ethbtc":0.027008,"usdtd":8.17,"bull":19,"weakBull":24,"bear":98,"rsiL3":157,"up7":58,"up7Total":226},{"t":1782189938453,"ethbtc":0.027012,"usdtd":8.18,"bull":17,"weakBull":20,"bear":136,"rsiL3":112,"up7":54,"up7Total":226},{"t":1782190181374,"ethbtc":0.026994,"usdtd":8.18,"bull":14,"weakBull":17,"bear":141,"rsiL3":103,"up7":54,"up7Total":226},{"t":1782190852336,"ethbtc":0.027025,"usdtd":8.2,"bull":13,"weakBull":18,"bear":148,"rsiL3":60,"up7":47,"up7Total":226},{"t":1782191740586,"ethbtc":0.027012,"usdtd":8.2,"bull":12,"weakBull":17,"bear":151,"rsiL3":54,"up7":47,"up7Total":226},{"t":1782192645183,"ethbtc":0.026998,"usdtd":8.23,"bull":12,"weakBull":16,"bear":158,"rsiL3":47,"up7":47,"up7Total":226},{"t":1782193537522,"ethbtc":0.027028,"usdtd":8.23,"bull":12,"weakBull":16,"bear":152,"rsiL3":51,"up7":47,"up7Total":226},{"t":1782194458085,"ethbtc":0.027024,"usdtd":8.23,"bull":9,"weakBull":13,"bear":151,"rsiL3":40,"up7":43,"up7Total":226},{"t":1782195339583,"ethbtc":0.027013,"usdtd":8.23,"bull":9,"weakBull":11,"bear":166,"rsiL3":25,"up7":38,"up7Total":226},{"t":1782196247163,"ethbtc":0.026865,"usdtd":8.32,"bull":6,"weakBull":8,"bear":173,"rsiL3":15,"up7":32,"up7Total":226},{"t":1782197139196,"ethbtc":0.026855,"usdtd":8.3,"bull":6,"weakBull":9,"bear":173,"rsiL3":17,"up7":33,"up7Total":226},{"t":1782198053312,"ethbtc":0.026885,"usdtd":8.29,"bull":9,"weakBull":12,"bear":181,"rsiL3":20,"up7":35,"up7Total":226},{"t":1782198943883,"ethbtc":0.026885,"usdtd":8.29,"bull":8,"weakBull":11,"bear":180,"rsiL3":30,"up7":35,"up7Total":226},{"t":1782199850512,"ethbtc":0.026873,"usdtd":8.28,"bull":6,"weakBull":9,"bear":179,"rsiL3":35,"up7":35,"up7Total":226},{"t":1782200743817,"ethbtc":0.02684,"usdtd":8.29,"bull":6,"weakBull":9,"bear":179,"rsiL3":27,"up7":34,"up7Total":226},{"t":1782201658467,"ethbtc":0.02677,"usdtd":8.29,"bull":5,"weakBull":8,"bear":188,"rsiL3":20,"up7":32,"up7Total":226},{"t":1782202543505,"ethbtc":0.026613,"usdtd":8.31,"bull":6,"weakBull":9,"bear":188,"rsiL3":16,"up7":30,"up7Total":226},{"t":1782203449549,"ethbtc":0.026489,"usdtd":8.39,"bull":5,"weakBull":7,"bear":189,"rsiL3":12,"up7":27,"up7Total":226},{"t":1782204344410,"ethbtc":0.026435,"usdtd":8.38,"bull":4,"weakBull":7,"bear":187,"rsiL3":15,"up7":28,"up7Total":226},{"t":1782205257470,"ethbtc":0.026436,"usdtd":8.37,"bull":7,"weakBull":9,"bear":192,"rsiL3":38,"up7":32,"up7Total":226},{"t":1782206144856,"ethbtc":0.026441,"usdtd":8.37,"bull":6,"weakBull":7,"bear":192,"rsiL3":50,"up7":34,"up7Total":226},{"t":1782207054198,"ethbtc":0.026452,"usdtd":8.36,"bull":7,"weakBull":8,"bear":190,"rsiL3":69,"up7":34,"up7Total":226},{"t":1782207941817,"ethbtc":0.02646,"usdtd":8.36,"bull":6,"weakBull":7,"bear":190,"rsiL3":41,"up7":33,"up7Total":226},{"t":1782208858913,"ethbtc":0.026471,"usdtd":8.37,"bull":7,"weakBull":8,"bear":183,"rsiL3":71,"up7":31,"up7Total":226},{"t":1782209741516,"ethbtc":0.026512,"usdtd":8.35,"bull":9,"weakBull":10,"bear":185,"rsiL3":94,"up7":31,"up7Total":226},{"t":1782210651644,"ethbtc":0.026517,"usdtd":8.37,"bull":7,"weakBull":10,"bear":187,"rsiL3":90,"up7":31,"up7Total":226},{"t":1782211545865,"ethbtc":0.026492,"usdtd":8.38,"bull":6,"weakBull":8,"bear":192,"rsiL3":58,"up7":29,"up7Total":226},{"t":1782211761272,"ethbtc":0.026505,"usdtd":8.38,"bull":6,"weakBull":8,"bear":190,"rsiL3":68,"up7":30,"up7Total":226},{"t":1782212460972,"ethbtc":0.026516,"usdtd":8.39,"bull":5,"weakBull":6,"bear":191,"rsiL3":149,"up7":29,"up7Total":226},{"t":1782213340506,"ethbtc":0.026537,"usdtd":8.38,"bull":7,"weakBull":8,"bear":186,"rsiL3":182,"up7":30,"up7Total":226},{"t":1782214251303,"ethbtc":0.02654,"usdtd":8.35,"bull":8,"weakBull":11,"bear":173,"rsiL3":196,"up7":30,"up7Total":226},{"t":1782215139592,"ethbtc":0.026578,"usdtd":8.35,"bull":9,"weakBull":10,"bear":160,"rsiL3":200,"up7":31,"up7Total":226},{"t":1782216057151,"ethbtc":0.02656,"usdtd":8.35,"bull":9,"weakBull":11,"bear":164,"rsiL3":189,"up7":29,"up7Total":226},{"t":1782216943458,"ethbtc":0.026557,"usdtd":8.36,"bull":7,"weakBull":10,"bear":167,"rsiL3":190,"up7":28,"up7Total":226},{"t":1782217849555,"ethbtc":0.026582,"usdtd":8.36,"bull":8,"weakBull":11,"bear":168,"rsiL3":186,"up7":28,"up7Total":226},{"t":1782218740786,"ethbtc":0.026597,"usdtd":8.36,"bull":7,"weakBull":9,"bear":163,"rsiL3":183,"up7":28,"up7Total":226},{"t":1782219658223,"ethbtc":0.026568,"usdtd":8.38,"bull":5,"weakBull":10,"bear":177,"rsiL3":185,"up7":32,"up7Total":226},{"t":1782220539708,"ethbtc":0.02657,"usdtd":8.39,"bull":5,"weakBull":10,"bear":174,"rsiL3":185,"up7":31,"up7Total":226},{"t":1782221454329,"ethbtc":0.026569,"usdtd":8.4,"bull":5,"weakBull":11,"bear":185,"rsiL3":171,"up7":31,"up7Total":226},{"t":1782222343221,"ethbtc":0.026583,"usdtd":8.37,"bull":7,"weakBull":12,"bear":100,"rsiL3":195,"up7":33,"up7Total":226},{"t":1782223260046,"ethbtc":0.02661,"usdtd":8.36,"bull":7,"weakBull":14,"bear":67,"rsiL3":182,"up7":40,"up7Total":226},{"t":1782224143836,"ethbtc":0.026578,"usdtd":8.36,"bull":8,"weakBull":13,"bear":44,"rsiL3":192,"up7":43,"up7Total":226},{"t":1782225055700,"ethbtc":0.026573,"usdtd":8.35,"bull":8,"weakBull":14,"bear":57,"rsiL3":189,"up7":42,"up7Total":226},{"t":1782225939650,"ethbtc":0.026608,"usdtd":8.34,"bull":7,"weakBull":13,"bear":79,"rsiL3":179,"up7":40,"up7Total":226},{"t":1782226862553,"ethbtc":0.026595,"usdtd":8.35,"bull":9,"weakBull":13,"bear":145,"rsiL3":178,"up7":37,"up7Total":226},{"t":1782227747414,"ethbtc":0.026563,"usdtd":8.36,"bull":8,"weakBull":13,"bear":163,"rsiL3":169,"up7":37,"up7Total":226},{"t":1782228656387,"ethbtc":0.026569,"usdtd":8.38,"bull":9,"weakBull":14,"bear":154,"rsiL3":171,"up7":37,"up7Total":226},{"t":1782229548026,"ethbtc":0.026575,"usdtd":8.36,"bull":6,"weakBull":11,"bear":162,"rsiL3":163,"up7":35,"up7Total":226},{"t":1782230472201,"ethbtc":0.026563,"usdtd":8.37,"bull":8,"weakBull":15,"bear":144,"rsiL3":51,"up7":37,"up7Total":226},{"t":1782231346566,"ethbtc":0.026563,"usdtd":8.34,"bull":7,"weakBull":15,"bear":63,"rsiL3":142,"up7":36,"up7Total":226},{"t":1782232257740,"ethbtc":0.026548,"usdtd":8.35,"bull":6,"weakBull":13,"bear":94,"rsiL3":111,"up7":35,"up7Total":226},{"t":1782233143785,"ethbtc":0.026547,"usdtd":8.35,"bull":7,"weakBull":14,"bear":90,"rsiL3":111,"up7":36,"up7Total":226},{"t":1782234057599,"ethbtc":0.026529,"usdtd":8.36,"bull":9,"weakBull":17,"bear":136,"rsiL3":108,"up7":31,"up7Total":226},{"t":1782234947121,"ethbtc":0.026551,"usdtd":8.37,"bull":6,"weakBull":13,"bear":166,"rsiL3":87,"up7":30,"up7Total":226},{"t":1782235854456,"ethbtc":0.026545,"usdtd":8.36,"bull":6,"weakBull":15,"bear":123,"rsiL3":131,"up7":30,"up7Total":226},{"t":1782236741405,"ethbtc":0.026542,"usdtd":8.35,"bull":7,"weakBull":14,"bear":149,"rsiL3":94,"up7":28,"up7Total":226},{"t":1782237658605,"ethbtc":0.026573,"usdtd":8.38,"bull":6,"weakBull":13,"bear":169,"rsiL3":89,"up7":26,"up7Total":226},{"t":1782238543437,"ethbtc":0.026581,"usdtd":8.37,"bull":6,"weakBull":14,"bear":151,"rsiL3":107,"up7":27,"up7Total":226},{"t":1782239448517,"ethbtc":0.026583,"usdtd":8.37,"bull":7,"weakBull":14,"bear":138,"rsiL3":129,"up7":28,"up7Total":226},{"t":1782240343935,"ethbtc":0.026562,"usdtd":8.38,"bull":7,"weakBull":13,"bear":161,"rsiL3":102,"up7":27,"up7Total":226},{"t":1782241261172,"ethbtc":0.026604,"usdtd":8.4,"bull":9,"weakBull":17,"bear":146,"rsiL3":95,"up7":30,"up7Total":226},{"t":1782242142496,"ethbtc":0.026612,"usdtd":8.37,"bull":9,"weakBull":19,"bear":115,"rsiL3":140,"up7":31,"up7Total":226},{"t":1782243053090,"ethbtc":0.026619,"usdtd":8.38,"bull":10,"weakBull":20,"bear":89,"rsiL3":158,"up7":36,"up7Total":226},{"t":1782243946382,"ethbtc":0.026612,"usdtd":8.37,"bull":10,"weakBull":20,"bear":129,"rsiL3":126,"up7":31,"up7Total":226},{"t":1782244861662,"ethbtc":0.026651,"usdtd":8.38,"bull":12,"weakBull":23,"bear":84,"rsiL3":183,"up7":31,"up7Total":226},{"t":1782245745861,"ethbtc":0.026645,"usdtd":8.36,"bull":11,"weakBull":22,"bear":53,"rsiL3":193,"up7":31,"up7Total":226},{"t":1782246652700,"ethbtc":0.02663,"usdtd":8.36,"bull":11,"weakBull":24,"bear":57,"rsiL3":192,"up7":31,"up7Total":226},{"t":1782247541186,"ethbtc":0.026618,"usdtd":8.36,"bull":11,"weakBull":24,"bear":59,"rsiL3":195,"up7":30,"up7Total":226},{"t":1782248456915,"ethbtc":0.026629,"usdtd":8.36,"bull":10,"weakBull":26,"bear":76,"rsiL3":178,"up7":32,"up7Total":226},{"t":1782249339413,"ethbtc":0.026644,"usdtd":8.35,"bull":10,"weakBull":28,"bear":50,"rsiL3":186,"up7":33,"up7Total":226},{"t":1782250247700,"ethbtc":0.026641,"usdtd":8.36,"bull":9,"weakBull":26,"bear":53,"rsiL3":186,"up7":34,"up7Total":226},{"t":1782251140905,"ethbtc":0.02662,"usdtd":8.35,"bull":9,"weakBull":25,"bear":54,"rsiL3":183,"up7":31,"up7Total":226}]}